CHANGES.txt
MANIFEST.in
README.rst
setup.py
quint/__init__.py
quint/quint.py
quint.egg-info/PKG-INFO
quint.egg-info/SOURCES.txt
quint.egg-info/dependency_links.txt
quint.egg-info/not-zip-safe
quint.egg-info/requires.txt
quint.egg-info/top_level.txt