Metadata-Version: 1.0
Name: quint
Version: 0.1
Summary: Quint is a minimal path finding library useful for discrete state scenarios
Home-page: http://github.com/lepisma/quint
Author: lepisma
Author-email: abhinav.tushar.vs@gmail.com
License: MIT
Keywords: q-learning reinforcement learning path finding
Platform: UNKNOWN
